python_wireguard/__init__.py
python_wireguard/client.py
python_wireguard/client_connection.py
python_wireguard/key.py
python_wireguard/server.py
python_wireguard/server_connection.py
python_wireguard/wireguard.py
python_wireguard/bin/py-wireguard.so
python_wireguard-0.2.2.dist-info/LICENSE
python_wireguard-0.2.2.dist-info/METADATA
python_wireguard-0.2.2.dist-info/WHEEL
python_wireguard-0.2.2.dist-info/top_level.txt
python_wireguard-0.2.2.dist-info/RECORD
