Metadata-Version: 2.1
Name: python_wireguard
Version: 0.2.2
Summary: A python wrapper for controlling Wireguard
Home-page: https://github.com/jarnoaxel/python-wireguard
Author: jarnoaxel
License: GPL-3.0-or-later
Keywords: vpn,wireguard
License-File: LICENSE
